<?xml version="1.0" encoding="utf-8"?>
<!DOCTYPE documentInfo>
<documentInfo url="/home/marca/Azureus Downloads/Entropy and its Physical Meaning - J. S. Dugdale/Entropy and its Physical Meaning - J. S. Dugdale/Entropy and its Physical Meaning - J. S. Dugdale.pdf" >
 <pageList/>
 <generalInfo>
  <history>
   <oldPage viewport="10;C2:0.499408:0.0864929:1" />
   <oldPage viewport="9;C2:0.499408:1.00118:1" />
   <oldPage viewport="10;C2:0.499408:0.0390995:1" />
   <oldPage viewport="9;C2:0.499408:1.00118:1" />
   <oldPage viewport="10;C2:0.499408:0.986967:1" />
   <oldPage viewport="11;C2:0.499419:0.963615:1" />
   <oldPage viewport="12;C2:0.499408:0.996445:1" />
   <oldPage viewport="13;C2:0.499408:0.982227:1" />
   <oldPage viewport="14;C2:0.499408:0.0201422:1" />
   <oldPage viewport="13;C2:0.499408:0.792654:1" />
   <current viewport="0;C2:0.499221:0.348:1" />
  </history>
  <views>
   <view name="PageView" >
    <zoom mode="0" value="0.9772728085517883" />
   </view>
  </views>
 </generalInfo>
</documentInfo>
