<?xml version="1.0" encoding="utf-8"?>
<!DOCTYPE documentInfo>
<documentInfo url="/home/marca/Documents/unsw_biography/B2B_Strategic_Intent.pdf" >
 <pageList/>
 <generalInfo>
  <history>
   <oldPage viewport="8;C2:0.49926:0.053814:1" />
   <oldPage viewport="7;C2:0.49926:0.000522466:1" />
   <oldPage viewport="6;C2:0.49963:0.0853786:1" />
   <oldPage viewport="5;C2:0.49963:0.594517:1" />
   <oldPage viewport="6;C2:0.49963:0.0853786:1" />
   <oldPage viewport="5;C2:0.518588:-0.371725:1" />
   <oldPage viewport="4;C2:0.49963:0.138642:1" />
   <oldPage viewport="3;C2:0.49963:0.648825:1" />
   <oldPage viewport="4;C2:0.49963:0.634726:1" />
   <oldPage viewport="5;C2:0.49963:0.798172:1" />
   <current viewport="6;C2:0.49963:0.28799:1" />
  </history>
  <views>
   <view name="PageView" >
    <zoom mode="1" value="3.25" />
   </view>
  </views>
 </generalInfo>
</documentInfo>
